<mvc:View xmlns:mvc="sap.ui.core.mvc" xmlns="sap.m" controllerName="com.mysap.mysapsemanticpage.controller.MySemanticPage" displayBlock="true">
    <SemanticPage xmlns="sap.f.semantic" showFooter="true" id="page0">
        <titleHeading>
            <m:Title xmlns:m="sap.m" text="Listagem de Produtos" id="idSemanticPageTitle"/>
        </titleHeading>

        <titleMainAction>
            <TitleMainAction text="Main Action" id="action0"/>
        </titleMainAction>

        <titleCustomTextActions>
            <m:Button xmlns:m="sap.m" text="Custom Text Button" id="button0"/>
        </titleCustomTextActions>

        <titleCustomIconActions>
            <m:OverflowToolbarButton xmlns:m="sap.m" icon="sap-icon://cart" text="Custom Icon Button" id="button1"/>
        </titleCustomIconActions>

        <footerCustomActions>
            <m:Button xmlns:m="sap.m" text="New" id="button2" press="handlerNew" icon="sap-icon://write-new-document"/>
        </footerCustomActions>

        <headerContent>
            <sap.ui.layout:HorizontalLayout xmlns:sap.ui.layout="sap.ui.layout" id="layout0">
                <sap.ui.layout:content>
                    <sap.ui.layout:VerticalLayout width="100%" id="layout1">
                        <sap.ui.layout:content>
                            <sap.m:ObjectAttribute text="Business" xmlns:sap.m="sap.m" id="attribute0" title="Functional Area"/>

                            <sap.m:ObjectAttribute text="PI Products Sofia" xmlns:sap.m="sap.m" id="attribute1" title="Cost Center:Cost Center"/>

                            <sap.m:ObjectAttribute text="office@piproucts.comv" xmlns:sap.m="sap.m" id="attribute2" title="Email"/>
                        </sap.ui.layout:content>
                    </sap.ui.layout:VerticalLayout>

                    <sap.ui.layout:VerticalLayout width="100%" id="layout3"/>

                    <sap.ui.layout:VerticalLayout width="100%" id="layout2">
                        <sap.ui.layout:content>
                            <sap.m:ObjectAttribute xmlns:sap.m="sap.m" id="attribute3" title="Availability"/>

                            <ObjectStatus xmlns="sap.m" text="In Stock" state="Success" id="status0"/>
                        </sap.ui.layout:content>
                    </sap.ui.layout:VerticalLayout>
                </sap.ui.layout:content>
            </sap.ui.layout:HorizontalLayout>
            <sap.m:Toolbar width="100%" xmlns:sap.m="sap.m" id="toolbar1">
                <sap.m:content>
                    <SearchField xmlns="sap.m" placeholder="Search for ..." search="handlerSearchProducts" id="searchProducts" width="40%"/>
                </sap.m:content>
            </sap.m:Toolbar>

        </headerContent>



        <!-- **************************************************** -->

        <titleExpandedHeading>
            <Text xmlns="sap.m" text="text expanded heading" id="text9"/>
        </titleExpandedHeading>

        <titleSnappedHeading>
            <Text xmlns="sap.m" text="bbbbbbbbbbbbb" id="text10"/>
        </titleSnappedHeading>

        <titleSnappedOnMobile>
            <Title xmlns="sap.m" text="ccccccccccccccccccc" id="title1"/>
        </titleSnappedOnMobile>

        <titleSnappedContent>
            <Text xmlns="sap.m" text="Lista de produtos para montar um supermercado: veja quais itens não podem faltar" id="text11"/>
        </titleSnappedContent>

        <titleExpandedContent>
            <Text xmlns="sap.m" text="Lista de produtos para montar um supermercado: veja quais itens não podem faltar" id="text12"/>
        </titleExpandedContent>

        <titleContent>
            <Text xmlns="sap.m" text="fffffffff" id="text13"/>
        </titleContent>


        <!-- **************************************************** -->

    <content>

        <sap.m:List id="listProducts" xmlns:sap.m="sap.m" >

            <sap.m:items >

                <sap.m:StandardListItem type="Navigation" id="item0" />

            </sap.m:items>

        </sap.m:List>

    </content>

    </SemanticPage>

</mvc:View>